game_utils/__init__.py
game_utils/rock_paper_scissors.py
s2t2_game_utils-1.2.dist-info/LICENSE.md
s2t2_game_utils-1.2.dist-info/METADATA
s2t2_game_utils-1.2.dist-info/WHEEL
s2t2_game_utils-1.2.dist-info/top_level.txt
s2t2_game_utils-1.2.dist-info/RECORD
