Metadata-Version: 2.1
Name: s2t2-game-utils
Version: 1.2
Summary: Gameplay logic for Rock-Paper-Scissors
Home-page: https://github.com/s2t2/game-utils-py
Author: MJ Rossetti
Author-email: datacreativellc@gmail.com
License: MIT
Keywords: rock paper scissors game
Platform: UNKNOWN
